openstarlab_phaselearn-0.0.2.dist-info/licenses/LICENSE.md
phase/__init__.py
phase/sports/__init__.py
phase/sports/main_class.py
phase/sports/soccer/__init__.py
phase/sports/soccer/dataloaders/__init__.py
phase/sports/soccer/dataloaders/data_module.py
phase/sports/soccer/inference/__init__.py
phase/sports/soccer/inference/inference.py
phase/sports/soccer/main_class_soccer/main.py
phase/sports/soccer/models/__init__.py
phase/sports/soccer/models/baller2vec.py
phase/sports/soccer/models/gat_transformer.py
phase/sports/soccer/models/gcn_transformer.py
phase/sports/soccer/models/transformer.py
phase/sports/soccer/trainers/__init__.py
phase/sports/soccer/trainers/train.py
phase/sports/soccer/utils/__init__.py
phase/sports/soccer/utils/augmentation.py
phase/sports/soccer/utils/evaluation.py
phase/sports/soccer/utils/load_train_data.py
phase/sports/soccer/utils/preprocessing.py
openstarlab_phaselearn-0.0.2.dist-info/METADATA
openstarlab_phaselearn-0.0.2.dist-info/WHEEL
openstarlab_phaselearn-0.0.2.dist-info/top_level.txt
openstarlab_phaselearn-0.0.2.dist-info/RECORD
