Metadata-Version: 2.4
Name: openstarlab-phaselearn
Version: 0.0.2
Summary: openstarlab phaselearn modeling package
Author-email: Kento Kuroda <kuroda.kento@image.iit.tsukuba.ac.jp>
License: Apache License 2.0
Project-URL: Homepage, https://github.com/open-starlab/PhaseLearn
Classifier: Programming Language :: Python :: 3
Classifier: License :: OSI Approved :: Apache Software License
Classifier: Operating System :: OS Independent
Requires-Python: >=3.8
License-File: LICENSE.md
Requires-Dist: pandas>=2.0.0
Requires-Dist: numpy>=1.23.0
Requires-Dist: torch>=2.0.0
Requires-Dist: torch-geometric
Requires-Dist: torchprofile
Requires-Dist: pyyaml
Requires-Dist: scikit-learn
Requires-Dist: scipy
Requires-Dist: matplotlib
Requires-Dist: matplotsoccer
Requires-Dist: optuna
Dynamic: license-file
